nexus/__init__.py
nexus/nexus_api.py
nexus/corr_analysis/__init__.py
nexus/corr_analysis/factor_analysis/__init__.py
nexus/corr_analysis/factor_analysis/factor_analysis.py
nexus/corr_analysis/graph/__init__.py
nexus/corr_analysis/graph/cluster_corr.py
nexus/corr_analysis/graph/graph_utils.py
nexus/corr_analysis/graph/threshold_search.py
nexus/corr_analysis/llm/__init__.py
nexus/corr_analysis/llm/assistant.py
nexus/corr_analysis/llm/chatbot.py
nexus/corr_cluster/__init__.py
nexus/corr_cluster/cluster_ui.py
nexus/corr_cluster/cluster_utils.py
nexus/data_ingestion/__init__.py
nexus/data_ingestion/connection.py
nexus/data_ingestion/data_ingestor.py
nexus/data_ingestion/data_profiler.py
nexus/data_ingestion/db_ops.py
nexus/data_prep/__init__.py
nexus/data_prep/label_data_source.py
nexus/data_prep/opendata_client.py
nexus/data_prep/profile_datasource.py
nexus/data_prep/retry.py
nexus/data_prep/spatial_patterns.json
nexus/data_prep/spatial_temeporal_labeller.py
nexus/data_prep/st_tbl_collector.py
nexus/data_prep/table_downloader.py
nexus/data_prep/temporal_patterns.json
nexus/data_search/__init__.py
nexus/data_search/commons.py
nexus/data_search/data_polygamy.py
nexus/data_search/db_ops.py
nexus/data_search/search_corr.py
nexus/data_search/search_db.py
nexus/db_connector/__init__.py
nexus/db_connector/database_connecter.py
nexus/db_connector/duckdb_connector.py
nexus/db_connector/postgres_connector.py
nexus/utils/__init__.py
nexus/utils/coordinate.py
nexus/utils/corr_utils.py
nexus/utils/correlation_sketch_utils.py
nexus/utils/data_model.py
nexus/utils/decorators.py
nexus/utils/granularity_utils.py
nexus/utils/io_utils.py
nexus/utils/profile_utils.py
nexus/utils/spatial_graph.py
nexus/utils/spatial_hierarchy.py
nexus/utils/time_point.py
nexus_corr_discovery-0.0.4.dist-info/LICENSE.txt
nexus_corr_discovery-0.0.4.dist-info/METADATA
nexus_corr_discovery-0.0.4.dist-info/WHEEL
nexus_corr_discovery-0.0.4.dist-info/top_level.txt
nexus_corr_discovery-0.0.4.dist-info/RECORD
