Metadata-Version: 2.1
Name: nexus-corr-discovery
Version: 0.0.4
Summary: Correlation discovery over collections of spatio-temporal datasets
Home-page: UNKNOWN
License: UNKNOWN
Platform: UNKNOWN
Requires-Python: >=3.8
Requires-Dist: wheel
Requires-Dist: dill==0.3.8
Requires-Dist: duckdb==1.0.0
Requires-Dist: factor-analyzer==0.5.1
Requires-Dist: geopandas==0.14.4
Requires-Dist: mmh3==4.1.0
Requires-Dist: networkx==3.1
Requires-Dist: numpy==1.24.4
Requires-Dist: pandas==2.0.3
Requires-Dist: pingouin==0.5.4
Requires-Dist: psycopg2-binary
Requires-Dist: pyvis==0.3.2
Requires-Dist: PyYAML==6.0.1
Requires-Dist: Requests==2.31.0
Requires-Dist: scikit-learn
Requires-Dist: scipy==1.14.1
Requires-Dist: Shapely==2.0.3
Requires-Dist: SQLAlchemy==2.0.25
Requires-Dist: tqdm==4.66.1
Requires-Dist: ipywidgets==7.6.5
